[
  {
    "ContainingType": "surveyapi.Controllers.AnswerController",
    "Method": "SubmitAnswer",
    "RelativePath": "api/Answer",
    "HttpMethod": "POST",
    "IsController": true,
    "Order": 0,
    "Parameters": [
      {
        "Name": "answer",
        "Type": "surveyapi.Models.Answer",
        "IsRequired": true
      }
    ],
    "ReturnTypes": [
      {
        "Type": "surveyapi.Models.Answer",
        "MediaTypes": [
          "text/plain",
          "application/json",
          "text/json"
        ],
        "StatusCode": 200
      }
    ]
  },
  {
    "ContainingType": "surveyapi.Controllers.AnswerController",
    "Method": "DeleteAnswer",
    "RelativePath": "api/Answer/{id}",
    "HttpMethod": "DELETE",
    "IsController": true,
    "Order": 0,
    "Parameters": [
      {
        "Name": "id",
        "Type": "System.Int32",
        "IsRequired": true
      }
    ],
    "ReturnTypes": []
  },
  {
    "ContainingType": "surveyapi.Controllers.AnswerController",
    "Method": "GetAnswersByQuestionId",
    "RelativePath": "api/Answer/question/{questionId}",
    "HttpMethod": "GET",
    "IsController": true,
    "Order": 0,
    "Parameters": [
      {
        "Name": "questionId",
        "Type": "System.Int32",
        "IsRequired": true
      }
    ],
    "ReturnTypes": [
      {
        "Type": "System.Collections.Generic.List\u00601[[surveyapi.Models.Answer, surveyapi, Version=1.0.0.0, Culture=neutral, PublicKeyToken=null]]",
        "MediaTypes": [
          "text/plain",
          "application/json",
          "text/json"
        ],
        "StatusCode": 200
      }
    ]
  },
  {
    "ContainingType": "surveyapi.Controllers.AnswerController",
    "Method": "GetAnswersBySurveyId",
    "RelativePath": "api/Answer/survey/{surveyId}",
    "HttpMethod": "GET",
    "IsController": true,
    "Order": 0,
    "Parameters": [
      {
        "Name": "surveyId",
        "Type": "System.Int32",
        "IsRequired": true
      }
    ],
    "ReturnTypes": [
      {
        "Type": "System.Collections.Generic.List\u00601[[surveyapi.Models.Answer, surveyapi, Version=1.0.0.0, Culture=neutral, PublicKeyToken=null]]",
        "MediaTypes": [
          "text/plain",
          "application/json",
          "text/json"
        ],
        "StatusCode": 200
      }
    ]
  },
  {
    "ContainingType": "surveyapi.Controllers.QuestionController",
    "Method": "GetQuestions",
    "RelativePath": "api/Question",
    "HttpMethod": "GET",
    "IsController": true,
    "Order": 0,
    "Parameters": [],
    "ReturnTypes": [
      {
        "Type": "System.Collections.Generic.List\u00601[[surveyapi.Models.Question, surveyapi, Version=1.0.0.0, Culture=neutral, PublicKeyToken=null]]",
        "MediaTypes": [
          "text/plain",
          "application/json",
          "text/json"
        ],
        "StatusCode": 200
      }
    ]
  },
  {
    "ContainingType": "surveyapi.Controllers.QuestionController",
    "Method": "CreateQuestion",
    "RelativePath": "api/Question",
    "HttpMethod": "POST",
    "IsController": true,
    "Order": 0,
    "Parameters": [
      {
        "Name": "question",
        "Type": "surveyapi.Models.Question",
        "IsRequired": true
      }
    ],
    "ReturnTypes": [
      {
        "Type": "surveyapi.Models.Question",
        "MediaTypes": [
          "text/plain",
          "application/json",
          "text/json"
        ],
        "StatusCode": 200
      }
    ]
  },
  {
    "ContainingType": "surveyapi.Controllers.QuestionController",
    "Method": "GetQuestion",
    "RelativePath": "api/Question/{id}",
    "HttpMethod": "GET",
    "IsController": true,
    "Order": 0,
    "Parameters": [
      {
        "Name": "id",
        "Type": "System.Int32",
        "IsRequired": true
      }
    ],
    "ReturnTypes": [
      {
        "Type": "surveyapi.Models.Question",
        "MediaTypes": [
          "text/plain",
          "application/json",
          "text/json"
        ],
        "StatusCode": 200
      }
    ]
  },
  {
    "ContainingType": "surveyapi.Controllers.QuestionController",
    "Method": "UpdateQuestion",
    "RelativePath": "api/Question/{id}",
    "HttpMethod": "PUT",
    "IsController": true,
    "Order": 0,
    "Parameters": [
      {
        "Name": "id",
        "Type": "System.Int32",
        "IsRequired": true
      },
      {
        "Name": "updatedQuestion",
        "Type": "surveyapi.Models.Question",
        "IsRequired": true
      }
    ],
    "ReturnTypes": []
  },
  {
    "ContainingType": "surveyapi.Controllers.QuestionController",
    "Method": "DeleteQuestion",
    "RelativePath": "api/Question/{id}",
    "HttpMethod": "DELETE",
    "IsController": true,
    "Order": 0,
    "Parameters": [
      {
        "Name": "id",
        "Type": "System.Int32",
        "IsRequired": true
      }
    ],
    "ReturnTypes": []
  },
  {
    "ContainingType": "surveyapi.Controllers.QuestionController",
    "Method": "AddOptionToQuestion",
    "RelativePath": "api/Question/{questionId}/options",
    "HttpMethod": "POST",
    "IsController": true,
    "Order": 0,
    "Parameters": [
      {
        "Name": "questionId",
        "Type": "System.Int32",
        "IsRequired": true
      },
      {
        "Name": "option",
        "Type": "surveyapi.Models.Option",
        "IsRequired": true
      }
    ],
    "ReturnTypes": [
      {
        "Type": "surveyapi.Models.Option",
        "MediaTypes": [
          "text/plain",
          "application/json",
          "text/json"
        ],
        "StatusCode": 200
      }
    ]
  },
  {
    "ContainingType": "surveyapi.Controllers.SurveyController",
    "Method": "GetSurveys",
    "RelativePath": "api/Survey",
    "HttpMethod": "GET",
    "IsController": true,
    "Order": 0,
    "Parameters": [],
    "ReturnTypes": [
      {
        "Type": "System.Collections.Generic.List\u00601[[surveyapi.Models.Survey, surveyapi, Version=1.0.0.0, Culture=neutral, PublicKeyToken=null]]",
        "MediaTypes": [
          "text/plain",
          "application/json",
          "text/json"
        ],
        "StatusCode": 200
      }
    ]
  },
  {
    "ContainingType": "surveyapi.Controllers.SurveyController",
    "Method": "CreateSurvey",
    "RelativePath": "api/Survey",
    "HttpMethod": "POST",
    "IsController": true,
    "Order": 0,
    "Parameters": [
      {
        "Name": "survey",
        "Type": "surveyapi.Models.Survey",
        "IsRequired": true
      }
    ],
    "ReturnTypes": []
  },
  {
    "ContainingType": "surveyapi.Controllers.SurveyController",
    "Method": "GetSurvey",
    "RelativePath": "api/Survey/{id}",
    "HttpMethod": "GET",
    "IsController": true,
    "Order": 0,
    "Parameters": [
      {
        "Name": "id",
        "Type": "System.Int32",
        "IsRequired": true
      }
    ],
    "ReturnTypes": [
      {
        "Type": "surveyapi.Models.Survey",
        "MediaTypes": [
          "text/plain",
          "application/json",
          "text/json"
        ],
        "StatusCode": 200
      }
    ]
  },
  {
    "ContainingType": "surveyapi.Controllers.SurveyController",
    "Method": "UpdateSurvey",
    "RelativePath": "api/Survey/{id}",
    "HttpMethod": "PUT",
    "IsController": true,
    "Order": 0,
    "Parameters": [
      {
        "Name": "id",
        "Type": "System.Int32",
        "IsRequired": true
      },
      {
        "Name": "updatedSurvey",
        "Type": "surveyapi.Models.Survey",
        "IsRequired": true
      }
    ],
    "ReturnTypes": []
  },
  {
    "ContainingType": "surveyapi.Controllers.SurveyController",
    "Method": "DeleteSurvey",
    "RelativePath": "api/Survey/{id}",
    "HttpMethod": "DELETE",
    "IsController": true,
    "Order": 0,
    "Parameters": [
      {
        "Name": "id",
        "Type": "System.Int32",
        "IsRequired": true
      }
    ],
    "ReturnTypes": []
  }
]